LICENSE
MANIFEST.in
README.md
requirements.txt
setup.cfg
setup.py
mixprop/__init__.py
mixprop/_version.py
mixprop/args.py
mixprop/constants.py
mixprop/hyperopt_utils.py
mixprop/hyperparameter_optimization.py
mixprop/interpret.py
mixprop/nn_utils.py
mixprop/rdkit.py
mixprop/sklearn_predict.py
mixprop/sklearn_train.py
mixprop/spectra_utils.py
mixprop/utils.py
mixprop/visc_pred_wrapper.py
mixprop.egg-info/PKG-INFO
mixprop.egg-info/SOURCES.txt
mixprop.egg-info/dependency_links.txt
mixprop.egg-info/not-zip-safe
mixprop.egg-info/requires.txt
mixprop.egg-info/top_level.txt
mixprop/curation_pipeline/T_logV_correlation.py
mixprop/curation_pipeline/__init__.py
mixprop/curation_pipeline/load_data.py
mixprop/curation_pipeline/pchip_interpolation.py
mixprop/curation_pipeline/pipeline.py
mixprop/curation_pipeline/remove_inconsistent.py
mixprop/curation_pipeline/remove_not_liquid.py
mixprop/curation_pipeline/remove_salts.py
mixprop/curation_pipeline/split_data.py
mixprop/curation_pipeline/utils.py
mixprop/curation_pipeline/write_data.py
mixprop/data/__init__.py
mixprop/data/data.py
mixprop/data/scaffold.py
mixprop/data/scaler.py
mixprop/data/utils.py
mixprop/features/__init__.py
mixprop/features/features_generators.py
mixprop/features/featurization.py
mixprop/features/utils.py
mixprop/models/__init__.py
mixprop/models/model.py
mixprop/models/mpn.py
mixprop/train/__init__.py
mixprop/train/cross_validate.py
mixprop/train/evaluate.py
mixprop/train/loss_functions.py
mixprop/train/make_predictions.py
mixprop/train/metrics.py
mixprop/train/molecule_fingerprint.py
mixprop/train/predict.py
mixprop/train/run_training.py
mixprop/train/train.py
tests/test_mixprop.py