Metadata-Version: 2.1
Name: mixprop
Version: 0.0.4
Summary: Viscosity prediction for binary liquid mixtures
Home-page: https://github.com/cbilodeau2/mixprop_viscosity
Author: Camille Bilodeau
Author-email: camille79bilodeau@gmail.com
License: MIT license
Keywords: mixprop
Classifier: Intended Audience :: Developers
Classifier: License :: OSI Approved :: MIT License
Classifier: Natural Language :: English
Classifier: Programming Language :: Python :: 3
Classifier: Programming Language :: Python :: 3.8
Classifier: Programming Language :: Python :: 3.9
Classifier: Programming Language :: Python :: 3.10
Classifier: Programming Language :: Python :: 3.11
Requires-Python: >=3.8
License-File: LICENSE
